PythonlandZh/404.html
PythonlandZh/CNAME
PythonlandZh/Dockerfile
PythonlandZh/LICENSE
PythonlandZh/LICENSE_ETC
PythonlandZh/NAV.md
PythonlandZh/README.md
PythonlandZh/SUMMARY.md
PythonlandZh/__init__.py
PythonlandZh/__main__.py
PythonlandZh/index.html
PythonlandZh/update.sh
PythonlandZh/asset/LXGWWenKaiScreen.ttf
PythonlandZh/asset/__init__.py
PythonlandZh/asset/back-to-top.css
PythonlandZh/asset/back-to-top.js
PythonlandZh/asset/dark-mode.css
PythonlandZh/asset/dark-mode.js
PythonlandZh/asset/docsify-apachecn-footer.js
PythonlandZh/asset/docsify-baidu-push.js
PythonlandZh/asset/docsify-baidu-stat.js
PythonlandZh/asset/docsify-clicker.js
PythonlandZh/asset/docsify-cnzz.js
PythonlandZh/asset/docsify-copy-code.min.js
PythonlandZh/asset/docsify-katex.js
PythonlandZh/asset/docsify-quick-page.css
PythonlandZh/asset/docsify-quick-page.js
PythonlandZh/asset/docsify-sidebar-collapse.min.js
PythonlandZh/asset/docsify.min.js
PythonlandZh/asset/edit.css
PythonlandZh/asset/edit.js
PythonlandZh/asset/edit.svg
PythonlandZh/asset/flygon_qr_alipay.png
PythonlandZh/asset/katex.min.css
PythonlandZh/asset/left.svg
PythonlandZh/asset/lxgw-wenkai.css
PythonlandZh/asset/moon.svg
PythonlandZh/asset/prism-c.min.js
PythonlandZh/asset/prism-cpp.min.js
PythonlandZh/asset/prism-csharp.min.js
PythonlandZh/asset/prism-darcula.css
PythonlandZh/asset/prism-java.min.js
PythonlandZh/asset/prism-javascript.min.js
PythonlandZh/asset/prism-php.min.js
PythonlandZh/asset/prism-python.min.js
PythonlandZh/asset/right.svg
PythonlandZh/asset/search.min.js
PythonlandZh/asset/share.css
PythonlandZh/asset/share.js
PythonlandZh/asset/share.svg
PythonlandZh/asset/sidebar.min.css
PythonlandZh/asset/style.css
PythonlandZh/asset/sun.svg
PythonlandZh/asset/up.svg
PythonlandZh/asset/vue.css
PythonlandZh/asset/fonts/KaTeX_AMS-Regular.ttf
PythonlandZh/asset/fonts/KaTeX_AMS-Regular.woff
PythonlandZh/asset/fonts/KaTeX_AMS-Regular.woff2
PythonlandZh/asset/fonts/KaTeX_Caligraphic-Bold.ttf
pythonland_zh-2022.9.11.1.dist-info/METADATA
pythonland_zh-2022.9.11.1.dist-info/WHEEL
pythonland_zh-2022.9.11.1.dist-info/entry_points.txt
pythonland_zh-2022.9.11.1.dist-info/top_level.txt
pythonland_zh-2022.9.11.1.dist-info/RECORD
